evalvault/__init__.py
evalvault/debug_ragas.py
evalvault/debug_ragas_real.py
evalvault/mkdocs_helpers.py
evalvault/adapters/__init__.py
evalvault/adapters/inbound/__init__.py
evalvault/adapters/inbound/api/__init__.py
evalvault/adapters/inbound/api/adapter.py
evalvault/adapters/inbound/api/main.py
evalvault/adapters/inbound/api/routers/__init__.py
evalvault/adapters/inbound/api/routers/benchmark.py
evalvault/adapters/inbound/api/routers/calibration.py
evalvault/adapters/inbound/api/routers/chat.py
evalvault/adapters/inbound/api/routers/config.py
evalvault/adapters/inbound/api/routers/domain.py
evalvault/adapters/inbound/api/routers/knowledge.py
evalvault/adapters/inbound/api/routers/mcp.py
evalvault/adapters/inbound/api/routers/pipeline.py
evalvault/adapters/inbound/api/routers/runs.py
evalvault/adapters/inbound/cli/__init__.py
evalvault/adapters/inbound/cli/app.py
evalvault/adapters/inbound/cli/commands/__init__.py
evalvault/adapters/inbound/cli/commands/agent.py
evalvault/adapters/inbound/cli/commands/analyze.py
evalvault/adapters/inbound/cli/commands/api.py
evalvault/adapters/inbound/cli/commands/artifacts.py
evalvault/adapters/inbound/cli/commands/benchmark.py
evalvault/adapters/inbound/cli/commands/calibrate.py
evalvault/adapters/inbound/cli/commands/calibrate_judge.py
evalvault/adapters/inbound/cli/commands/compare.py
evalvault/adapters/inbound/cli/commands/config.py
evalvault/adapters/inbound/cli/commands/debug.py
evalvault/adapters/inbound/cli/commands/domain.py
evalvault/adapters/inbound/cli/commands/experiment.py
evalvault/adapters/inbound/cli/commands/gate.py
evalvault/adapters/inbound/cli/commands/generate.py
evalvault/adapters/inbound/cli/commands/graph_rag.py
evalvault/adapters/inbound/cli/commands/history.py
evalvault/adapters/inbound/cli/commands/init.py
evalvault/adapters/inbound/cli/commands/kg.py
evalvault/adapters/inbound/cli/commands/langfuse.py
evalvault/adapters/inbound/cli/commands/method.py
evalvault/adapters/inbound/cli/commands/ops.py
evalvault-1.76.0.dist-info/METADATA
evalvault-1.76.0.dist-info/WHEEL
evalvault-1.76.0.dist-info/entry_points.txt
evalvault-1.76.0.dist-info/licenses/LICENSE.md
evalvault-1.76.0.dist-info/RECORD
