Metadata-Version: 2.4
Name: evalvault
Version: 1.76.0
Summary: RAG evaluation system using Ragas with Phoenix/Langfuse tracing
Project-URL: Homepage, https://github.com/ntts9990/EvalVault
Project-URL: Documentation, https://github.com/ntts9990/EvalVault#readme
Project-URL: Repository, https://github.com/ntts9990/EvalVault.git
Project-URL: Issues, https://github.com/ntts9990/EvalVault/issues
Project-URL: Changelog, https://github.com/ntts9990/EvalVault/releases
Author: EvalVault Contributors
Maintainer: EvalVault Contributors
License: Apache-2.0
License-File: LICENSE.md
Keywords: ai,evaluation,langfuse,llm,machine-learning,nlp,observability,opentelemetry,phoenix,rag,ragas,retrieval-augmented-generation,testing
Classifier: Development Status :: 4 - Beta
Classifier: Intended Audience :: Developers
Classifier: Intended Audience :: Science/Research
Classifier: License :: OSI Approved :: Apache Software License
Classifier: Operating System :: OS Independent
Classifier: Programming Language :: Python :: 3
Classifier: Programming Language :: Python :: 3.12
Classifier: Programming Language :: Python :: 3.13
Classifier: Topic :: Scientific/Engineering :: Artificial Intelligence
Classifier: Topic :: Software Development :: Quality Assurance
Classifier: Topic :: Software Development :: Testing
Classifier: Typing :: Typed
Requires-Python: >=3.12
Requires-Dist: chainlit>=2.9.5
Requires-Dist: chardet
Requires-Dist: fastapi>=0.128.0
Requires-Dist: instructor
Requires-Dist: langchain-openai
Requires-Dist: langfuse
Requires-Dist: matplotlib<3.9.0,>=3.8.0
Requires-Dist: networkx
Requires-Dist: openai
Requires-Dist: openpyxl
Requires-Dist: pandas
Requires-Dist: pydantic
Requires-Dist: pydantic-settings
Requires-Dist: pypdf>=4.3.0
Requires-Dist: python-multipart
Requires-Dist: ragas==0.4.2
Requires-Dist: rich
Requires-Dist: truststore>=0.10.4
Requires-Dist: typer
Requires-Dist: uvicorn>=0.40.0
Requires-Dist: xlrd
Provides-Extra: analysis
Requires-Dist: scikit-learn>=1.3.0; extra == 'analysis'
Requires-Dist: xgboost>=2.0.0; extra == 'analysis'
Provides-Extra: anthropic
Requires-Dist: anthropic; extra == 'anthropic'
Requires-Dist: langchain-anthropic; extra == 'anthropic'
Provides-Extra: benchmark
Requires-Dist: datasets>=2.0.0; extra == 'benchmark'
Requires-Dist: lm-eval[api]>=0.4.0; extra == 'benchmark'
Provides-Extra: dashboard
Requires-Dist: matplotlib<3.9.0,>=3.8.0; extra == 'dashboard'
Provides-Extra: dev
Requires-Dist: anthropic; extra == 'dev'
Requires-Dist: arize-phoenix>=8.0.0; extra == 'dev'
Requires-Dist: datasets>=2.0.0; extra == 'dev'
Requires-Dist: faiss-cpu>=1.8.0; extra == 'dev'
Requires-Dist: ijson>=3.3.0; extra == 'dev'
Requires-Dist: kiwipiepy>=0.18.0; extra == 'dev'
Requires-Dist: langchain-anthropic; extra == 'dev'
Requires-Dist: lm-eval[api]>=0.4.0; extra == 'dev'
Requires-Dist: mkdocs-material>=9.5.0; extra == 'dev'
Requires-Dist: mkdocs>=1.5.0; extra == 'dev'
Requires-Dist: mkdocstrings[python]>=0.24.0; extra == 'dev'
Requires-Dist: mlflow>=2.0.0; extra == 'dev'
Requires-Dist: openinference-instrumentation-langchain>=0.1.0; extra == 'dev'
Requires-Dist: opentelemetry-api>=1.20.0; extra == 'dev'
Requires-Dist: opentelemetry-exporter-otlp>=1.20.0; extra == 'dev'
Requires-Dist: opentelemetry-sdk>=1.20.0; extra == 'dev'
Requires-Dist: pgvector>=0.2.5; extra == 'dev'
Requires-Dist: psycopg[binary]>=3.0.0; extra == 'dev'
Requires-Dist: pydeps>=3.0.1; extra == 'dev'
Requires-Dist: pymdown-extensions>=10.7.0; extra == 'dev'
Requires-Dist: pytest; extra == 'dev'
Requires-Dist: pytest-asyncio; extra == 'dev'
Requires-Dist: pytest-cov; extra == 'dev'
Requires-Dist: pytest-html; extra == 'dev'
Requires-Dist: pytest-mock; extra == 'dev'
Requires-Dist: pytest-rerunfailures; extra == 'dev'
Requires-Dist: pytest-xdist; extra == 'dev'
Requires-Dist: python-multipart; extra == 'dev'
Requires-Dist: rank-bm25>=0.2.2; extra == 'dev'
Requires-Dist: ruff; extra == 'dev'
Requires-Dist: scikit-learn<1.4.0,>=1.3.0; extra == 'dev'
Requires-Dist: sentence-transformers>=5.2.0; extra == 'dev'
Requires-Dist: xgboost>=2.0.0; extra == 'dev'
Provides-Extra: docs
Requires-Dist: mkdocs-material>=9.5.0; extra == 'docs'
Requires-Dist: mkdocs>=1.5.0; extra == 'docs'
Requires-Dist: mkdocstrings[python]>=0.24.0; extra == 'docs'
Requires-Dist: pymdown-extensions>=10.7.0; extra == 'docs'
Provides-Extra: korean
Requires-Dist: kiwipiepy>=0.18.0; extra == 'korean'
Requires-Dist: rank-bm25>=0.2.2; extra == 'korean'
Requires-Dist: sentence-transformers>=5.2.0; extra == 'korean'
Provides-Extra: mlflow
Requires-Dist: mlflow>=2.0.0; extra == 'mlflow'
Provides-Extra: perf
Requires-Dist: faiss-cpu>=1.8.0; extra == 'perf'
Requires-Dist: ijson>=3.3.0; extra == 'perf'
Provides-Extra: phoenix
Requires-Dist: arize-phoenix>=8.0.0; extra == 'phoenix'
Requires-Dist: openinference-instrumentation-langchain>=0.1.0; extra == 'phoenix'
Requires-Dist: opentelemetry-api>=1.20.0; extra == 'phoenix'
Requires-Dist: opentelemetry-exporter-otlp>=1.20.0; extra == 'phoenix'
Requires-Dist: opentelemetry-sdk>=1.20.0; extra == 'phoenix'
Provides-Extra: postgres
Requires-Dist: pgvector>=0.2.5; extra == 'postgres'
Requires-Dist: psycopg[binary]>=3.0.0; extra == 'postgres'
Provides-Extra: secrets
Requires-Dist: boto3; extra == 'secrets'
Requires-Dist: google-cloud-secret-manager; extra == 'secrets'
Requires-Dist: hvac; extra == 'secrets'
Provides-Extra: timeseries
Requires-Dist: aeon>=1.3.0; extra == 'timeseries'
Requires-Dist: numba>=0.55.0; extra == 'timeseries'
Provides-Extra: web
